wiserHeatAPIv2/__init__.py
wiserHeatAPIv2/cli.py
wiserHeatAPIv2/const.py
wiserHeatAPIv2/device.py
wiserHeatAPIv2/devices.py
wiserHeatAPIv2/discovery.py
wiserHeatAPIv2/exceptions.py
wiserHeatAPIv2/heating.py
wiserHeatAPIv2/heating_actuator.py
wiserHeatAPIv2/hot_water.py
wiserHeatAPIv2/light.py
wiserHeatAPIv2/moments.py
wiserHeatAPIv2/rest_controller.py
wiserHeatAPIv2/room.py
wiserHeatAPIv2/roomstat.py
wiserHeatAPIv2/schedule.py
wiserHeatAPIv2/shutter.py
wiserHeatAPIv2/smartplug.py
wiserHeatAPIv2/smartvalve.py
wiserHeatAPIv2/system.py
wiserHeatAPIv2/ufh.py
wiserHeatAPIv2/wiserhub.py
wiserHeatAPIv2/helpers/__init__.py
wiserHeatAPIv2/helpers/battery.py
wiserHeatAPIv2/helpers/capabilities.py
wiserHeatAPIv2/helpers/cloud.py
wiserHeatAPIv2/helpers/firmware.py
wiserHeatAPIv2/helpers/gps.py
wiserHeatAPIv2/helpers/network.py
wiserHeatAPIv2/helpers/opentherm.py
wiserHeatAPIv2/helpers/signal.py
wiserHeatAPIv2/helpers/special_times.py
wiserHeatAPIv2/helpers/temp.py
wiserHeatAPIv2/helpers/zigbee.py
wiserHeatAPIv2-0.0.42.dist-info/LICENSE
wiserHeatAPIv2-0.0.42.dist-info/METADATA
wiserHeatAPIv2-0.0.42.dist-info/WHEEL
wiserHeatAPIv2-0.0.42.dist-info/entry_points.txt
wiserHeatAPIv2-0.0.42.dist-info/top_level.txt
wiserHeatAPIv2-0.0.42.dist-info/RECORD
