Metadata-Version: 2.1
Name: wiserHeatAPIv2
Version: 0.0.42
Summary: An API for controlling the Drayton Wiser Heating system
Home-page: https://github.com/msp1974/wiserheatapiv2
Author: Mark Parker
Author-email: msparker@sky.com
Classifier: Development Status :: 4 - Beta
Classifier: Intended Audience :: Developers
Classifier: Programming Language :: Python :: 3
Classifier: License :: OSI Approved :: MIT License
Classifier: Operating System :: OS Independent
Requires-Python: >=3.9
License-File: LICENSE
Requires-Dist: ruamel.yaml (==0.16.12)
Requires-Dist: zeroconf
Requires-Dist: requests
